<?xml version="1.0"?>
<!--<!DOCTYPE metadata SYSTEM "http://www.esri.com/metadata/esriprof80.dtd">-->
<metadata xml:lang="ja"><Esri><MetaID>{0D4BFCBD-D59A-4CAA-BA7F-99A49026F10B}</MetaID><CreaDate>20080602</CreaDate><CreaTime>11004400</CreaTime><SyncOnce>TRUE</SyncOnce><DataProperties><lineage><Process Name="Create Feature Class" ToolSource="C:\Program Files\ArcGIS\ArcToolbox\Toolboxes\Data Management Tools.tbx\CreateFeatureclass" Date="20080602" Time="110044">CreateFeatureclass L:\product\gmpink\vct roadl # roadl_Layer SAME_AS_TEMPLATE SAME_AS_TEMPLATE "GEOGCS['GCS_WGS_1984',DATUM['D_WGS_1984',SPHEROID['WGS_1984',6378137.0,298.257223563]],PRIMEM['Greenwich',0.0],UNIT['Degree',0.0174532925199433]];-96.054432 -21.054432 31999999.970198;0.000000 100000.000000;0.000000 100000.000000" # 0 0 0 L:\product\gmpink\vct\roadl.shp</Process><Process Name="Append" ToolSource="C:\Program Files\ArcGIS\ArcToolbox\Toolboxes\Data Management Tools.tbx\Append" Date="20080602" Time="110049">Append roadl_Layer L:\product\gmpink\vct\roadl.shp TEST L:\product\gmpink\vct\roadl.shp</Process><Process Name="FeatureClassToFeatureClass_25" ToolSource="C:\Program Files\ArcGIS\ArcToolbox\Toolboxes\Conversion Tools.tbx\FeatureClassToFeatureClass" Date="20080602" Time="110050">FeatureClassToFeatureClass L:\product\GMv1\VCT\globalm\area:trans\roadl L:\product\gmpink\vct roadl # "f_code f_code VISIBLE;f_code description f_code_des VISIBLE;acc acc VISIBLE;acc description acc_descri VISIBLE;exs exs VISIBLE;exs description exs_descri VISIBLE;med med VISIBLE;med description med_descri VISIBLE;rst rst VISIBLE;rst description rst_descri VISIBLE;rsu rsu VISIBLE;rsu description rsu_descri VISIBLE;rtt rtt VISIBLE;rtt description rtt_descri VISIBLE;soc soc VISIBLE;tile_id tile_id VISIBLE;edg_id edg_id VISIBLE" SAME_AS_TEMPLATE SAME_AS_TEMPLATE # 0 L:\product\gmpink\vct\roadl.shp</Process></lineage></DataProperties></Esri></metadata>
